synchronous_fifo.v
module synchronous_fifo #(parameter DEPTH = 8, DATA_WIDTH =8)(
    input clk,reset_n,
    input write_en, read_en,
    input [DATA_WIDTH-1:0] in,
    output reg [DATA_WIDTH-1:0] out,
    output full, empty
    //output wrap_around
    

     
);

    parameter ptr_width = $clog2(DEPTH);
    reg [ptr_width:0] write_ptr;
    reg [ptr_width:0] read_ptr;
    reg [DATA_WIDTH-1:0] fifo[0:DEPTH-1];
    //reg wrap_around;

    //Setting values to default whenever actice low reset arrives// Synchronous Reset
    always@(posedge clk) begin
        if(reset_n == 0) begin
            write_ptr<=0;
            read_ptr<=0;
            out<=0;
            //wrap_around<=0;
            end
        end

    //Writing Data to the FIFO
    always@(posedge clk) begin
        if(write_en & !full) begin  
            fifo[write_ptr] <= in;
            write_ptr <= write_ptr +1;
            end
        end 

    //Reading Data from the FIFO
    always@(posedge clk) begin
        if(read_en &!empty) begin
            out<= fifo[read_ptr]  ;
            read_ptr <= read_ptr +1;
            end
    end
    
    //@(posedge clk) wrap_around <= write_ptr[ptr_width] ^ read_ptr[ptr_width];
    //assign wrap_around = write_ptr[ptr_width] ^ read_ptr[ptr_width];

    //Condition for full
    assign full = (write_ptr[ptr_width] != read_ptr[ptr_width]) && (write_ptr[ptr_width -1:0] == read_ptr[ptr_width-1:0]);
    // COndition for empty
    assign empty = (write_ptr == read_ptr);


endmodule

t_synchronous_fifo.v
`include "synchronous_fifo.v"

module t_synchronous_fifo;

    parameter DATA_WIDTH = 8;
    parameter DEPTH = 8;
    wire [DATA_WIDTH-1:0] data_out;
    wire full;
    wire empty;

    reg clk, rst_n;
    reg w_en, r_en;
    reg [DATA_WIDTH-1:0] data_in;

    reg [DATA_WIDTH-1:0] wdata_q[0:DEPTH-1];
    integer i,j;

    // Instantiate the FIFO
    synchronous_fifo #(.DEPTH(DEPTH), .DATA_WIDTH(DATA_WIDTH)) s_fifo(
        .clk(clk), 
        .reset_n(rst_n), 
        .write_en(w_en), 
        .read_en(r_en), 
        .in(data_in), 
        .out(data_out), 
        .full(full), 
        .empty(empty)
    );

    // Clock generation
    initial begin 
        clk = 0; 
        forever #5 clk = ~clk; 
    end

    // Write operations
    initial begin
        rst_n = 0;
        w_en = 0;
        data_in = 0;
        #15 rst_n = 1;  // Release reset after some time

        for (i = 0; i < DEPTH; i++) begin
            @(posedge clk);
            w_en = 1;
            data_in = i + 1;  // Writing sequential data
            wdata_q[i] = data_in;  // Store data for later comparison
        end
        w_en = 0;  // Stop writing after filling the FIFO
    end

    // Read operations and comparison
    initial begin
        r_en = 0;
        #100;  // Wait for write operations to complete

        for (i = 0; i < DEPTH; i++) begin
            @(posedge clk);
            r_en = 1;
            #1;
            if (data_out != wdata_q[i])
                $error("Time = %0t: Comparison Failed: expected data = %h, read data = %h", $time, wdata_q[i], data_out);
            else
                $display("Time = %0t: Comparison Passed: expected data = %h, read data = %h", $time, wdata_q[i], data_out);
        end
        r_en = 0;  // Stop reading after emptying the FIFO

        #50;  // Wait some time before finishing the simulation
        $finish;
    end

    // Dump waveform data
    initial begin
        $dumpfile("t_synchronous_fifo2.vcd");
        $dumpvars(0, t_synchronous_fifo);
    end

endmodule

t_synchronous_fifo.vcd
$date
	Sun Jul 14 00:37:40 2024
$end
$version
	Icarus Verilog
$end
$timescale
	1s
$end
$scope module t_synchronous_fifo $end
$var wire 1 ! full $end
$var wire 1 " empty $end
$var wire 8 # data_out [7:0] $end
$var parameter 32 $ DATA_WIDTH $end
$var parameter 32 % DEPTH $end
$var reg 1 & clk $end
$var reg 8 ' data_in [7:0] $end
$var reg 1 ( r_en $end
$var reg 1 ) rst_n $end
$var reg 1 * w_en $end
$var integer 32 + i [31:0] $end
$scope module s_fifo $end
$var wire 1 & clk $end
$var wire 1 ! full $end
$var wire 8 , in [7:0] $end
$var wire 1 ( read_en $end
$var wire 1 ) reset_n $end
$var wire 1 * write_en $end
$var wire 1 " empty $end
$var parameter 32 - DATA_WIDTH $end
$var parameter 32 . DEPTH $end
$var parameter 32 / ptr_width $end
$var reg 8 0 out [7:0] $end
$var reg 4 1 read_ptr [3:0] $end
$var reg 4 2 write_ptr [3:0] $end
$upscope $end
$upscope $end
$enddefinitions $end
$comment Show the parameter values. $end
$dumpall
b11 /
b1000 .
b1000 -
b1000 %
b1000 $
$end
#0
$dumpvars
bx 2
bx 1
bx 0
b0 ,
bx +
0*
0)
0(
b0 '
0&
bx #
x"
x!
$end
#5
0!
b0 #
b0 0
1"
b0 1
b0 2
1&
#10
0&
#15
0"
b1 2
b1 '
b1 ,
1*
1&
b1 +
1)
#20
0&
#25
b10 2
b10 +
b10 '
b10 ,
1&
#30
0&
#35
b11 2
b11 +
b11 '
b11 ,
1&
#40
0&
#45
b100 2
b100 +
b100 '
b100 ,
1&
#50
0&
#55
b101 2
b101 +
b101 '
b101 ,
1&
#60
0&
#65
b110 2
b110 +
b110 '
b110 ,
1&
#70
0&
#75
b111 2
b111 +
b111 '
b111 ,
1&
#80
0&
#85
1!
b1000 2
0*
b1000 +
b1000 '
b1000 ,
1&
#90
0&
#95
1&
#100
0&
b0 +
#105
0!
b1 1
b1 #
b1 0
1(
1&
#106
b1 +
#110
0&
#115
b10 1
1&
#116
b10 +
#120
0&
#125
b11 1
b11 #
b11 0
1&
#126
b11 +
#130
0&
#135
b100 1
1&
#136
b100 +
#140
0&
#145
b101 1
b101 #
b101 0
1&
#146
b101 +
#150
0&
#155
b110 1
1&
#156
b110 +
#160
0&
#165
b111 1
b111 #
b111 0
1&
#166
b111 +
#170
0&
#175
0!
1"
b1000 1
1&
#176
0(
b1000 +
